Workbook

Sheet 计算器
A1: 公积金反推收入、五险权益与用工成本计算器
A3: 输入参数（蓝字可修改） | E3: 反推结果与适用状态
A4: 双边公积金实缴额 | B4: 5400 | C4: 元/月 | E4: 原始反推公积金基数 | F4: =IFERROR($B$4/($B$5+$B$6),0) -> 22500
A5: 个人公积金缴存比例 | B5: 0.12 | C5: 比例 | E5: 反推状态 | F5: =IF($B$5+$B$6<=0,"比例错误",IF(F4>$B$8+0.01,"输入不一致：反推基数高于上限",IF(ABS(F4-$B$8)<=0.01,"达到上限：仅能判断工资不低于上限",IF(F4<$B$7-0.01,"达到下限或输入异常：无法精确反推","区间内：可近似反推缴存基数")))) -> 区间内：可近似反推缴存基数
A6: 单位公积金缴存比例 | B6: 0.12 | C6: 比例 | E6: 公积金缴存基数 | F6: =MAX($B$7,MIN(F4,$B$8)) -> 22500
A7: 公积金基数下限 | B7: 2500 | C7: 元/月；按缴存年度更新 | E7: 估算来源 | F7: =IF($B$17>0,"使用手工输入的当前月税前工资","使用公积金缴存基数反推值") -> 使用公积金缴存基数反推值
A8: 公积金基数上限 | B8: 41112 | C8: 元/月；按缴存年度更新 | E8: 用于估算的月工资 | F8: =IF($B$17>0,$B$17,F6) -> 22500
A9: 个人五险合计比例（自动汇总） | B9: =五险权益!$B$11 -> 0.1 | C9: 在“五险权益”工作表修改分项比例 | E9: 社保缴费基数（综合估算） | F9: =MAX($B$11,MIN(F8,$B$12)) -> 22500
A10: 单位五险合计比例（自动汇总） | B10: =五险权益!$C$11 -> 0.25 | C10: 在“五险权益”工作表修改分项比例 | E10: 口径提示 | F10: 公积金反推值通常对应缴存基数；达到上下限时只能得到边界，不能精确确定实际工资。
A11: 社保基数下限（独立输入） | B11: 2500 | C11: 不得直接引用公积金下限
A12: 社保基数上限（独立输入） | B12: 41112 | C12: 不得直接引用公积金上限
A13: 专项附加扣除 | B13: 0 | C13: 元/月
A14: 其他税前扣除 | B14: 0 | C14: 元/月
A15: 其他单位福利成本 | B15: 0 | C15: 元/月；食堂、企业年金等
A16: 计算月数 | B16: 12 | C16: 月
A17: 当前月税前工资（可选） | B17: 0 | C17: 0 表示使用公积金反推值
A20: 月度结果 | E20: 年度结果（现金、账户权益、风险保障分开展示）
A21: 税前月工资（估算口径） | B21: =$F$8 -> 22500 | C21: 元/月 | E21: 年度税前现金工资 | F21: =B21*$B$16 -> 270000 | G21: 元/年
A22: 个人公积金 | B22: =$F$6*$B$5 -> 2700 | C22: 元/月；进入个人公积金账户 | E22: 年度现金到手 | F22: =B32*$B$16 -> 197400 | G22: 元/年；现金口径
A23: 单位公积金 | B23: =$F$6*$B$6 -> 2700 | C23: 元/月；进入个人公积金账户 | E23: 年度公积金账户新增 | F23: =(B22+B23)*$B$16 -> 64800 | G23: 元/年；个人公积金账户
A24: 个人五险缴费 | B24: =五险权益!$L$9 -> 2250 | C24: 元/月；从工资中扣缴 | E24: 年度个人社保账户增加 | F24: =B26*$B$16 -> 27000 | G24: 元/年；养老、医保个人账户
A25: 单位五险缴费 | B25: =五险权益!$L$10 -> 5625 | C25: 元/月；单位承担 | E25: 年度个人可量化综合权益 | F25: =B34*$B$16 -> 289200 | G25: 元/年；现金＋公积金＋个人社保账户
A26: 个人社保账户权益增加 | B26: =五险权益!$L$11 -> 2250 | C26: 元/月；养老、医保个人账户实际划入 | E26: 年度个人五险缴费 | F26: =B24*$B$16 -> 27000 | G26: 元/年；缴费额
A27: 统筹及风险保障投入 | B27: =五险权益!$L$12 -> 5625 | C27: 元/月；统筹与风险保障，不等同个人资产 | E27: 年度单位五险缴费 | F27: =B25*$B$16 -> 67500 | G27: 元/年；单位成本
A28: 月应纳税所得额（年均口径） | B28: =MAX(0,B21-B22-B24-参数说明!$B$4-$B$13-$B$14) -> 12550 | C28: 元/月 | E28: 年度统筹及风险保障投入 | F28: =B27*$B$16 -> 67500 | G28: 元/年；不作为个人资产
A29: 预计全年应纳税所得额 | B29: =B28*$B$16 -> 150600 | C29: 元/年 | E29: 年度五险一金缴费总额 | F29: =(B22+B23+B24+B25)*$B$16 -> 159300 | G29: 元/年；仅表示缴费总额
A30: 预计全年个税 | B30: =IF(B29<=0,0,B29*INDEX(参数说明!$B$7:$B$13,MATCH(B29,参数说明!$A$7:$A$13,1))-INDEX(参数说明!$C$7:$C$13,MATCH(B29,参数说明!$A$7:$A$13,1))) -> 13200 | C30: 元/年 | E30: 年度单位用工成本 | F30: =B35*$B$16 -> 369900 | G30: 元/年；单位成本口径
A31: 预计月均个税 | B31: =IF($B$16<=0,0,B30/$B$16) -> 1100 | C31: 元/月；全年平均值 | E31: 年度其他单位福利成本 | F31: =$B$15*$B$16 -> 0 | G31: 元/年
A32: 月现金到手 | B32: =B21-B22-B24-B31 -> 16450 | C32: 元/月；可支配现金 | E32: 年度个人所得税 | F32: =B30 -> 13200 | G32: 元/年
A33: 月现金及公积金权益 | B33: =B32+B22+B23 -> 21850 | C33: 元/月；现金＋双边公积金
A34: 月个人可量化综合权益 | B34: =B33+B26 -> 24100 | C34: 元/月；现金＋双边公积金＋个人社保账户
A35: 单位月用工成本 | B35: =B21+B23+B25+$B$15 -> 30825 | C35: 元/月；不扣个人所得税
A38: 口径说明
A39: 1 | B39: “个人可量化综合权益”采用保守口径：现金到手＋双边公积金＋养老和医保个人账户实际增加额。
A40: 2 | B40: 统筹基金以及失业、工伤、生育风险保障具有真实保障价值，但不能按缴费原额直接认定为个人收入或个人资产。
A41: 3 | B41: 五险分项比例和个人账户划入率均在“五险权益”工作表维护；默认值只是保持原合计比例的结构示例。
A42: 4 | B42: “年度统筹及风险保障投入”单独披露，用于体现保障投入，但不加入个人可量化综合权益。
A43: 5 | B43: “情景折算五险权益”只用于敏感性分析，主结果始终采用保守口径，避免任意系数造成虚假精确。

Sheet 参数说明
A1: 参数、税率表与来源
A3: 参数名称 | B3: 数值 | C3: 单位 | D3: 说明 | E3: 来源
A4: 基本减除费用（月） | B4: 5000 | C4: 元/月 | D4: 用于居民个人综合所得年度估算 | E4: https://guangdong.chinatax.gov.cn/gdsw/fssw_nsrxt_kjxz/2025-10/09/content_b02be06c906e46bca00673beb9e7783a.shtml
A5: 综合所得个人所得税年度税率表
A6: 全年应纳税所得额下限 | B6: 税率 | C6: 速算扣除数 | D6: 适用区间 | E6: 来源
A7: 0 | B7: 0.03 | C7: 0 | D7: 不超过 36,000 元 | E7: https://guangdong.chinatax.gov.cn/gdsw/fssw_nsrxt_kjxz/2025-10/09/content_b02be06c906e46bca00673beb9e7783a.shtml
A8: 36000 | B8: 0.1 | C8: 2520 | D8: 超过 36,000 元至 144,000 元 | E8: 同上
A9: 144000 | B9: 0.2 | C9: 16920 | D9: 超过 144,000 元至 300,000 元 | E9: 同上
A10: 300000 | B10: 0.25 | C10: 31920 | D10: 超过 300,000 元至 420,000 元 | E10: 同上
A11: 420000 | B11: 0.3 | C11: 52920 | D11: 超过 420,000 元至 660,000 元 | E11: 同上
A12: 660000 | B12: 0.35 | C12: 85920 | D12: 超过 660,000 元至 960,000 元 | E12: 同上
A13: 960000 | B13: 0.45 | C13: 181920 | D13: 超过 960,000 元 | E13: 同上
A15: 维护提示 | D15: 公积金与社保基数上下限、缴费比例具有地区和年度差异，请在“计算器”输入区按实际政策更新。
A17: 五险权益模块说明
A18: 默认比例性质 | D18: 五险分项默认值用于保持原个人10%、单位25%的合计比例，不代表特定地区的最新法定费率。
A19: 个人账户口径 | D19: 只有实际划入个人名下养老、医保账户的金额进入保守口径综合权益。
A20: 统筹风险口径 | D20: 养老、医保统筹以及失业、工伤、生育投入单独披露，不直接加到个人收入。

Sheet 五险权益
A1: 五险缴费拆分与权益折算 | K1: 参数与汇总
A3: 蓝字为可修改参数。默认采用保守口径：只有养老、医疗个人账户的实际划入额计入“可量化五险权益”；统筹与风险保障不计入个人资产。 | K3: 社保缴费基数 | L3: =计算器!$F$9 -> 22500 | M3: 元/月；来自计算器
K4: 计算月数 | L4: =计算器!$B$16 -> 12 | M4: 月；来自计算器
A5: 险种 | B5: 个人缴费率 | C5: 单位缴费率 | D5: 个人账户划入率 | E5: 个人月缴费 | F5: 单位月缴费 | G5: 个人账户月增加 | H5: 统筹/风险保障月投入 | I5: 权益处理 | K5: 个人账户现值系数 | L5: 1 | M5: 情景参数；主结果按名义额100%
A6: 养老保险 | B6: 0.08 | C6: 0.16 | D6: 0.08 | E6: =$L$3*B6 -> 1800 | F6: =$L$3*C6 -> 3600 | G6: =$L$3*D6 -> 1800 | H6: =E6+F6-G6 -> 3600 | I6: 个人账户划入额可量化；统筹部分不按缴费额计入个人资产 | K6: 统筹/风险折算系数 | L6: 0 | M6: 情景参数；默认0%，不进入主结果
A7: 医疗保险 | B7: 0.02 | C7: 0.06 | D7: 0.02 | E7: =$L$3*B7 -> 450 | F7: =$L$3*C7 -> 1350 | G7: =$L$3*D7 -> 450 | H7: =E7+F7-G7 -> 1350 | I7: 个人账户实际划入额可量化；统筹部分作为医疗保障
A8: 失业保险 | B8: 0 | C8: 0.005 | D8: 0 | E8: =$L$3*B8 -> 0 | F8: =$L$3*C8 -> 112.5 | G8: =$L$3*D8 -> 0 | H8: =E8+F8-G8 -> 112.5 | I8: 风险保险；满足失业待遇条件时产生给付 | K8: 月度汇总
A9: 工伤保险 | B9: 0 | C9: 0.005 | D9: 0 | E9: =$L$3*B9 -> 0 | F9: =$L$3*C9 -> 112.5 | G9: =$L$3*D9 -> 0 | H9: =E9+F9-G9 -> 112.5 | I9: 风险保险；发生并认定工伤时产生给付 | K9: 个人五险缴费 | L9: =E11 -> 2250 | M9: 元/月
A10: 生育保险 | B10: 0 | C10: 0.02 | D10: 0 | E10: =$L$3*B10 -> 0 | F10: =$L$3*C10 -> 450 | G10: =$L$3*D10 -> 0 | H10: =E10+F10-G10 -> 450 | I10: 风险保险；满足生育待遇条件时产生给付 | K10: 单位五险缴费 | L10: =F11 -> 5625 | M10: 元/月
A11: 合计 | B11: =SUM(B6:B10) -> 0.1 | C11: =SUM(C6:C10) -> 0.25 | D11: =SUM(D6:D10) -> 0.1 | E11: =SUM(E6:E10) -> 2250 | F11: =SUM(F6:F10) -> 5625 | G11: =SUM(G6:G10) -> 2250 | H11: =SUM(H6:H10) -> 5625 | K11: 个人社保账户增加 | L11: =G11 -> 2250 | M11: 元/月；可明确归属个人账户
K12: 统筹及风险保障投入 | L12: =H11 -> 5625 | M12: 元/月；不等同于个人资产
K13: 保守口径五险权益 | L13: =G11 -> 2250 | M13: 元/月；主结果采用
A14: 使用说明 | K14: 情景折算五险权益 | L14: =G11*$L$5+H11*$L$6 -> 2250 | M14: 元/月；仅供情景分析
A15: 1 | B15: 默认比例只是结构示例，并用于保持原计算器个人10%、单位25%的合计比例。请按所在地、单位和年度政策修改。
A16: 2 | B16: “个人账户划入率”应填写实际进入个人名下账户的比例，不一定等于个人缴费率。 | K16: 年度汇总
A17: 3 | B17: 保守口径只认可个人账户增加额；单位养老、医保统筹及失业、工伤、生育投入不直接折算为个人收入。 | K17: 年度个人五险缴费 | L17: =L9*$L$4 -> 27000 | M17: 元/年
A18: 4 | B18: 情景折算允许对个人账户和统筹风险投入设置系数，但主计算器不会采用统筹/风险折算结果。 | K18: 年度单位五险缴费 | L18: =L10*$L$4 -> 67500 | M18: 元/年
A19: 5 | B19: 精确养老金现值需要年龄、退休年龄、缴费年限、养老金计发基数等精算参数，本表未将其伪装成确定金额。 | K19: 年度个人社保账户增加 | L19: =L11*$L$4 -> 27000 | M19: 元/年
K20: 年度统筹及风险保障投入 | L20: =L12*$L$4 -> 67500 | M20: 元/年
K21: 年度情景折算五险权益 | L21: =L14*$L$4 -> 27000 | M21: 元/年
