Workbook

Sheet 计算器
A1: 公积金反推收入与用工成本计算器（修正版）
A3: 输入参数（蓝字可修改） | E3: 反推结果与适用状态
A4: 双边公积金实缴额 | B4: 9867 | C4: 元/月 | E4: 原始反推公积金基数 | F4: =IFERROR($B$4/($B$5+$B$6),0) -> 41112.5
A5: 个人公积金缴存比例 | B5: 0.12 | C5: 比例 | E5: 反推状态 | F5: =IF($B$5+$B$6<=0,"比例错误",IF(F4>$B$8+0.01,"输入不一致：反推基数高于上限",IF(ABS(F4-$B$8)<=0.01,"达到上限：仅能判断工资不低于上限",IF(F4<$B$7-0.01,"达到下限或输入异常：无法精确反推","区间内：可近似反推缴存基数")))) -> 输入不一致：反推基数高于上限
A6: 单位公积金缴存比例 | B6: 0.12 | C6: 比例 | E6: 公积金缴存基数 | F6: =MAX($B$7,MIN(F4,$B$8)) -> 41112
A7: 公积金基数下限 | B7: 2500 | C7: 元/月；按缴存年度更新 | E7: 估算来源 | F7: =IF($B$17>0,"使用手工输入的当前月税前工资","使用公积金缴存基数反推值") -> 使用公积金缴存基数反推值
A8: 公积金基数上限 | B8: 41112 | C8: 元/月；按缴存年度更新 | E8: 用于估算的月工资 | F8: =IF($B$17>0,$B$17,F6) -> 41112
A9: 个人社保综合比例（估算） | B9: 0.1 | C9: 简化口径 | E9: 社保缴费基数（综合估算） | F9: =MAX($B$11,MIN(F8,$B$12)) -> 41112
A10: 单位社保综合比例（估算） | B10: 0.25 | C10: 简化口径 | E10: 口径提示 | F10: 公积金反推值通常对应缴存基数；达到上下限时只能得到边界，不能精确确定实际工资。
A11: 社保基数下限（独立输入） | B11: 2500 | C11: 不得直接引用公积金下限
A12: 社保基数上限（独立输入） | B12: 41112 | C12: 不得直接引用公积金上限
A13: 专项附加扣除 | B13: 0 | C13: 元/月
A14: 其他税前扣除 | B14: 0 | C14: 元/月
A15: 其他单位福利成本 | B15: 0 | C15: 元/月；食堂、企业年金等
A16: 计算月数 | B16: 12 | C16: 月
A17: 当前月税前工资（可选） | B17: 0 | C17: 0 表示使用公积金反推值
A20: 月度结果 | E20: 年度结果（不同经济口径分开展示）
A21: 税前月工资（估算口径） | B21: =$F$8 -> 41112 | C21: 元/月 | E21: 年度税前现金工资 | F21: =B21*$B$16 -> 493344 | G21: 元/年
A22: 个人公积金 | B22: =$F$6*$B$5 -> 4933.44 | C22: 元/月；进入个人公积金账户 | E22: 年度现金到手 | F22: =B30*$B$16 -> 335526.24 | G22: 元/年；现金口径
A23: 单位公积金 | B23: =$F$6*$B$6 -> 4933.44 | C23: 元/月；进入个人公积金账户 | E23: 年度公积金账户新增 | F23: =(B22+B23)*$B$16 -> 118402.56 | G23: 元/年；个人账户资产新增
A24: 个人社保缴费（综合估算） | B24: =$F$9*$B$9 -> 4111.2 | C24: 元/月；不等同于个人资产 | E24: 年度现金及公积金权益 | F24: =B31*$B$16 -> 453928.8 | G24: 元/年；现金＋公积金权益
A25: 单位社保缴费（综合估算） | B25: =$F$9*$B$10 -> 10278 | C25: 元/月；主要形成社保统筹权益 | E25: 年度个人社保缴费 | F25: =B24*$B$16 -> 49334.4 | G25: 元/年；单独披露
A26: 月应纳税所得额（年均口径） | B26: =MAX(0,B21-B22-B24-参数说明!$B$4-$B$13-$B$14) -> 27067.36 | C26: 元/月 | E26: 年度单位社保缴费 | F26: =B25*$B$16 -> 123336 | G26: 元/年；不作为个人收入
A27: 预计全年应纳税所得额 | B27: =B26*$B$16 -> 324808.32 | C27: 元/年 | E27: 年度五险一金缴费总额 | F27: =(B22+B23+B24+B25)*$B$16 -> 291072.96 | G27: 元/年；仅表示缴费总额
A28: 预计全年个税 | B28: =IF(B27<=0,0,B27*INDEX(参数说明!$B$7:$B$13,MATCH(B27,参数说明!$A$7:$A$13,1))-INDEX(参数说明!$C$7:$C$13,MATCH(B27,参数说明!$A$7:$A$13,1))) -> 49282.08 | C28: 元/年 | E28: 年度单位用工成本 | F28: =B32*$B$16 -> 675881.28 | G28: 元/年；单位成本口径
A29: 预计月均个税 | B29: =IF($B$16<=0,0,B28/$B$16) -> 4106.84 | C29: 元/月；全年平均值 | E29: 年度其他单位福利成本 | F29: =$B$15*$B$16 -> 0 | G29: 元/年
A30: 月现金到手 | B30: =B21-B22-B24-B29 -> 27960.52 | C30: 元/月；可支配现金 | E30: 年度个人所得税 | F30: =B28 -> 49282.08 | G30: 元/年
A31: 月现金及公积金权益 | B31: =B30+B22+B23 -> 37827.4 | C31: 元/月；含流动性受限的公积金 | E31: 激进口径综合权益（详见“五险权益-激进口径”）
A32: 单位月用工成本 | B32: =B21+B23+B25+$B$15 -> 56323.44 | C32: 元/月；不扣个人所得税 | E32: 年度五险权益估值 | F32: ='五险权益-激进口径'!$H$24 -> 150385.8 | G32: 元/年；概率期望＋养老金现值
E33: 年度激进综合权益 | F33: ='五险权益-激进口径'!$H$25 -> 604314.6 | G33: 元/年；非可兑现收入
E34: 月均激进综合权益 | F34: ='五险权益-激进口径'!$H$26 -> 50359.55 | G34: 元/月；仅作情景比较
A35: 口径说明
A36: 1 | B36: 公积金反推的是缴存基数，通常反映上一年度月平均工资口径，不必然等于当前月工资。
A37: 2 | B37: 反推值触及缴存上下限时，只能判断工资的边界；表中“用于估算的月工资”属于边界或近似值。
A38: 3 | B38: 社保部分采用综合比例简化估算，社保上下限已与公积金上下限分离；精确核算时应按险种分别设置。
A39: 4 | B39: 现金到手、公积金个人账户新增、社保缴费和单位用工成本分别展示，不再使用“一年实际获得”这一混合概念。
A40: 5 | B40: 个税按全年综合所得估算；“预计月均个税”是全年税额的平均值，不代表每月实际预扣金额。

Sheet 参数说明
A1: 参数、税率表与来源
A3: 参数名称 | B3: 数值 | C3: 单位 | D3: 说明 | E3: 来源
A4: 基本减除费用（月） | B4: 5000 | C4: 元/月 | D4: 用于居民个人综合所得年度估算 | E4: https://guangdong.chinatax.gov.cn/gdsw/fssw_nsrxt_kjxz/2025-10/09/content_b02be06c906e46bca00673beb9e7783a.shtml
A5: 综合所得个人所得税年度税率表
A6: 全年应纳税所得额下限 | B6: 税率 | C6: 速算扣除数 | D6: 适用区间 | E6: 来源
A7: 0 | B7: 0.03 | C7: 0 | D7: 不超过 36,000 元 | E7: https://guangdong.chinatax.gov.cn/gdsw/fssw_nsrxt_kjxz/2025-10/09/content_b02be06c906e46bca00673beb9e7783a.shtml
A8: 36000 | B8: 0.1 | C8: 2520 | D8: 超过 36,000 元至 144,000 元 | E8: 同上
A9: 144000 | B9: 0.2 | C9: 16920 | D9: 超过 144,000 元至 300,000 元 | E9: 同上
A10: 300000 | B10: 0.25 | C10: 31920 | D10: 超过 300,000 元至 420,000 元 | E10: 同上
A11: 420000 | B11: 0.3 | C11: 52920 | D11: 超过 420,000 元至 660,000 元 | E11: 同上
A12: 660000 | B12: 0.35 | C12: 85920 | D12: 超过 660,000 元至 960,000 元 | E12: 同上
A13: 960000 | B13: 0.45 | C13: 181920 | D13: 超过 960,000 元 | E13: 同上
A15: 维护提示 | D15: 公积金与社保基数上下限、缴费比例具有地区和年度差异，请在“计算器”输入区按实际政策更新。

Sheet 五险权益-激进口径
A1: 五险权益激进口径估值模型（概率期望值＋养老金现值）
A3: 基础与养老假设（蓝字可修改） | F3: 主计算器链接与养老金估值
A4: 当前年龄 | B4: 30 | C4: 岁 | D4: 情景假设；按实际年龄修改 | F4: 当前年度税前工资 | G4: =计算器!$F$21 -> 493344 | H4: 元/年
A5: 开始参保年龄 | B5: 30 | C5: 岁 | D5: 用于将终身养老金现值分摊到职业期 | F5: 当前月社保缴费基数 | G5: =计算器!$F$9 -> 41112 | H5: 元/月
A6: 退休年龄 | B6: 63 | C6: 岁 | D6: 情景假设；不代表法定退休年龄 | F6: 年度现金及公积金权益 | G6: =计算器!$F$24 -> 453928.8 | H6: 元/年
A7: 预期寿命 | B7: 90 | C7: 岁 | D7: 情景假设 | F7: 距离退休年数 | G7: =MAX(0,$B$6-$B$4) -> 33 | H7: 年
A8: 折现率 | B8: 0.035 | C8: 年 | D8: 用于把未来待遇折算为当前价值 | F8: 预计领取养老金年数 | G8: =MAX(0,$B$7-$B$6) -> 27 | H8: 年
A9: 退休前工资增长率 | B9: 0.03 | C9: 年 | D9: 情景假设 | F9: 预计职业缴费年数 | G9: =MAX(1,$B$6-$B$5) -> 33 | H9: 年
A10: 退休后养老金增长率 | B10: 0.02 | C10: 年 | D10: 情景假设 | F10: 退休时预计年度工资 | G10: =G4*(1+$B$9)^G7 -> 1308513.7 | H10: 元/年
A11: 基础养老金替代率 | B11: 0.35 | C11: 退休首年工资比例 | D11: 全职业期估值参数，不含个人账户 | F11: 退休首年基础养老金 | G11: =G10*$B$11 -> 457979.79 | H11: 元/年
A12: 养老个人账户划入率 | B12: 0.08 | C12: 社保基数比例 | D12: 仅用于权益估值，不回写主计算器缴费 | F12: 退休时点养老金现值 | G12: =IF(G8<=0,0,IF(ABS($B$8-$B$10)<0.000001,G11*G8/(1+$B$8),G11*(1-((1+$B$10)/(1+$B$8))^G8)/($B$8-$B$10))) -> 9946067.5 | H12: 元
A13: 医保个人账户划入率 | B13: 0.02 | C13: 社保基数比例 | D13: 按实际地区及年龄政策修改 | F13: 养老金现值（当前时点） | G13: =G12/(1+$B$8)^G7 -> 3196096.3 | H13: 元
F14: 基础养老金年化权益 | G14: =G13/G9 -> 96851.404 | H14: 元/年
F15: 养老个人账户年度新增 | G15: =G5*$B$12*12 -> 39467.52 | H15: 元/年
F16: 医保个人账户年度新增 | G16: =G5*$B$13*12 -> 9866.88 | H16: 元/年
A18: 风险保障期望给付（年事件概率 × 预期待遇 × 适用系数） | G18: 激进口径汇总
A19: 险种 | B19: 年事件概率 | C19: 预期待遇 | D19: 适用系数 | E19: 年期望给付 | G19: 年度现金及公积金权益 | H19: =G6 -> 453928.8 | I19: 元/年
A20: 医疗保险 | B20: 0.25 | C20: 8000 | D20: 1 | E20: =B20*C20*D20 -> 2000 | G20: 养老个人账户年度新增 | H20: =G15 -> 39467.52 | I20: 元/年
A21: 失业保险 | B21: 0.05 | C21: 18000 | D21: 1 | E21: =B21*C21*D21 -> 900 | G21: 医保个人账户年度新增 | H21: =G16 -> 9866.88 | I21: 元/年
A22: 工伤保险 | B22: 0.005 | C22: 80000 | D22: 1 | E22: =B22*C22*D22 -> 400 | G22: 基础养老金年化权益 | H22: =G14 -> 96851.404 | I22: 元/年
A23: 生育保险 | B23: 0.03 | C23: 30000 | D23: 1 | E23: =B23*C23*D23 -> 900 | G23: 风险保障年期望给付 | H23: =E24 -> 4200 | I23: 元/年
A24: 风险保障年期望给付合计 | E24: =SUM(E20:E23) -> 4200 | G24: 年度五险权益估值 | H24: =SUM(H20:H23) -> 150385.8 | I24: 元/年
G25: 年度激进综合权益 | H25: =H19+H24 -> 604314.6 | I25: 元/年
G26: 月均激进综合权益 | H26: =IF(计算器!$B$16<=0,0,H25/计算器!$B$16) -> 50359.55 | I26: 元/月
G27: 激进综合权益/税前工资 | H27: =IF(计算器!$F$21=0,0,H25/计算器!$F$21) -> 1.2249355 | I27: 倍
G28: 年度单位用工成本 | H28: =计算器!$F$28 -> 675881.28 | I28: 元/年
G29: 激进权益/单位成本 | H29: =IF(H28=0,0,H25/H28) -> 0.89411354 | I29: 倍
A34: 模型说明与风险提示
A35: 1 | B35: 本模型属于“激进口径”：把风险保险按概率期望值计入，并把未来基础养老金现值按预计职业缴费年数年化。结果不是可兑现收入。
A36: 2 | B36: 事件概率、预期待遇、适用系数、替代率、寿命和折现率均为情景假设。黄色底蓝字单元格应由用户按个人情况调整。
A37: 3 | B37: 基础养老金年化权益是对终身待遇现值的分摊近似；未模拟政策变化、缴费中断、生存概率、养老金计发基数和地区差异。
A38: 4 | B38: 养老及医保个人账户按名义年度新增计入；风险保险期望值不代表当年必然领取，也不能与现金等价。
A39: 5 | B39: “年度激进综合权益”＝现金及公积金权益＋养老/医保个人账户新增＋基础养老金年化权益＋风险保障期望给付。
